{
  "dependencies": [
    {
      "name": "lime",
      "type": "git",
      "dir": null,
      "ref": null,
      "url": "https://github.com/HomuHomu833-haxelibs/lime-wip"
    },
    {
      "name": "openfl",
      "type": "git",
      "dir": null,
      "ref": null,
      "url": "https://github.com/FNF-SE/openfl"
    },
    {
      "name": "flixel",
      "type": "git",
      "dir": null,
      "ref": null,
      "url": "https://github.com/FNF-SE/flixel"
    },
    {
      "name": "flixel-addons",
      "type": "git",
      "dir": null,
      "ref": null,
      "url": "https://github.com/FNF-SE/flixel-addons"
    },
    {
      "name": "flixel-ui",
      "type": "git",
      "dir": null,
      "ref": null,
      "url": "https://github.com/FNF-SE/flixel-ui"
    },
    {
      "name": "hxcpp",
      "type": "git",
      "dir": null,
      "ref": null,
      "url": "https://github.com/HomuHomu833-haxelibs/hxcpp"
    },
    {
      "name": "SScript",
      "type": "git",
      "dir": null,
      "ref": null,
      "url": "https://github.com/FNF-SE/SScript"
    },
    {
      "name": "hxdiscord_rpc",
      "type": "haxelib",
      "version": null
    },
    {
      "name": "hxluajit",
      "type": "git",
      "dir": null,
      "ref": null,
      "url": "https://github.com/FNF-SE/hxluajit"
    },
    {
      "name": "hxgamemode",
      "type": "haxelib",
      "version": null
    },
    {
      "name": "format",
      "type": "haxelib",
      "version": null
    },
    {
      "name": "hxp",
      "type": "haxelib",
      "version": null
    },
    {
      "name": "hxvlc",
      "type": "git",
      "dir": null,
      "ref": null,
      "url": "https://github.com/FNF-SE/hxvlc"
    }
  ]
}
